ruurd_photos_ml/__init__.py
ruurd_photos_ml/analysis/__init__.py
ruurd_photos_ml/analysis/base_model.py
ruurd_photos_ml/analysis/getters.py
ruurd_photos_ml/analysis/utils.py
ruurd_photos_ml/analysis/caption/__init__.py
ruurd_photos_ml/analysis/caption/instruct_blip_captioner.py
ruurd_photos_ml/analysis/caption/protocol.py
ruurd_photos_ml/analysis/caption/sf_blip_captioner.py
ruurd_photos_ml/analysis/embedding/__init__.py
ruurd_photos_ml/analysis/embedding/open_clip_embedder.py
ruurd_photos_ml/analysis/embedding/protocol.py
ruurd_photos_ml/analysis/embedding/zero_clip_embedder.py
ruurd_photos_ml/analysis/facial_recognition/__init__.py
ruurd_photos_ml/analysis/facial_recognition/insight_facial_recognition.py
ruurd_photos_ml/analysis/facial_recognition/protocol.py
ruurd_photos_ml/analysis/llm/__init__.py
ruurd_photos_ml/analysis/llm/gemma_llm.py
ruurd_photos_ml/analysis/llm/protocol.py
ruurd_photos_ml/analysis/object_detection/__init__.py
ruurd_photos_ml/analysis/object_detection/protocol.py
ruurd_photos_ml/analysis/object_detection/resnet_object_detection.py
ruurd_photos_ml/analysis/ocr/__init__.py
ruurd_photos_ml/analysis/ocr/protocol.py
ruurd_photos_ml/analysis/ocr/resnet_tesseract_ocr.py
ruurd_photos_ml-0.2.2.dist-info/METADATA
ruurd_photos_ml-0.2.2.dist-info/WHEEL
ruurd_photos_ml-0.2.2.dist-info/RECORD
