Metadata-Version: 2.4
Name: ruurd-photos-ml
Version: 0.2.2
Summary: Some image related machine learning methods, to be used by Ruurd Photos.
Project-URL: Homepage, https://github.com/RuurdBijlsma/ruurd-photos-ml
Project-URL: Repository, https://github.com/RuurdBijlsma/ruurd-photos-ml
Project-URL: Documentation, https://ruurdbijlsma.github.io/ruurd-photos-ml
Author-email: Ruurd Bijlsma <ruurd@bijlsma.dev>
License-Expression: MIT
Requires-Python: >=3.12
Requires-Dist: accelerate>=1.11.0
Requires-Dist: hf-xet>=1.1.10
Requires-Dist: insightface>=0.7.3
Requires-Dist: onnxruntime-gpu>=1.23.0
Requires-Dist: onnxruntime>=1.23.1
Requires-Dist: open-clip-torch>=3.2.0
Requires-Dist: opencv-python>=4.12.0.88
Requires-Dist: pillow>=11.3.0
Requires-Dist: pytesseract>=0.3.13
Requires-Dist: torch>=2.8.0
Requires-Dist: torchvision>=0.23.0
Requires-Dist: transformers>=4.57.0
